[
null,
{"id":1,"members":[{"enemyId":1,"x":336,"y":436,"hidden":false},{"enemyId":1,"x":480,"y":436,"hidden":false}],"name":"こうもり*2","pages":[{"conditions":{"actorHp":50,"actorId":1,"actorValid":false,"enemyHp":50,"enemyIndex":0,"enemyValid":false,"switchId":1,"switchValid":false,"turnA":0,"turnB":0,"turnEnding":true,"turnValid":false},"list":[{"code":122,"indent":0,"parameters":[75,75,0,3,0,66,0]},{"code":0,"indent":0,"parameters":[]}],"span":1}]},
{"id":2,"members":[{"enemyId":96,"x":153,"y":343,"hidden":false},{"enemyId":96,"x":315,"y":277,"hidden":false},{"enemyId":96,"x":276,"y":444,"hidden":false}],"name":"サイボーグ　Ｃソルジャー*3","pages":[{"conditions":{"actorHp":50,"actorId":1,"actorValid":false,"enemyHp":50,"enemyIndex":0,"enemyValid":false,"switchId":1,"switchValid":false,"turnA":0,"turnB":0,"turnEnding":false,"turnValid":true},"list":[{"code":124,"indent":0,"parameters":[1]},{"code":0,"indent":0,"parameters":[]}],"span":0}]},
{"id":3,"members":[{"enemyId":95,"x":183,"y":343,"hidden":false},{"enemyId":95,"x":378,"y":301,"hidden":true},{"enemyId":95,"x":273,"y":444,"hidden":true}],"name":"エネミーソルジャー*3","pages":[{"conditions":{"actorHp":50,"actorId":1,"actorValid":false,"enemyHp":50,"enemyIndex":0,"enemyValid":false,"switchId":1,"switchValid":false,"turnA":0,"turnB":0,"turnEnding":false,"turnValid":true},"list":[{"code":124,"indent":0,"parameters":[1]},{"code":101,"indent":0,"parameters":["",2,0,2]},{"code":401,"indent":0,"parameters":["見張り"]},{"code":401,"indent":0,"parameters":["「侵入者を発見！戦闘に入る！」"]},{"code":101,"indent":0,"parameters":["",2,1,2]},{"code":401,"indent":0,"parameters":["本部"]},{"code":401,"indent":0,"parameters":["「了解、増援部隊を送る 侵入者を排除せよ！」"]},{"code":0,"indent":0,"parameters":[]}],"span":0},{"conditions":{"actorHp":50,"actorId":1,"actorValid":false,"enemyHp":50,"enemyIndex":0,"enemyValid":false,"switchId":1,"switchValid":false,"turnA":3,"turnB":3,"turnEnding":false,"turnValid":true},"list":[{"code":101,"indent":0,"parameters":["",2,0,2]},{"code":401,"indent":0,"parameters":["ミノコマンド"]},{"code":401,"indent":0,"parameters":["「報告にあった侵入者を確認、支援する！」"]},{"code":335,"indent":0,"parameters":[1]},{"code":0,"indent":0,"parameters":[]}],"span":0},{"conditions":{"actorHp":50,"actorId":1,"actorValid":false,"enemyHp":50,"enemyIndex":0,"enemyValid":false,"switchId":1,"switchValid":false,"turnA":5,"turnB":5,"turnEnding":false,"turnValid":true},"list":[{"code":101,"indent":0,"parameters":["",2,0,2]},{"code":401,"indent":0,"parameters":["ミノコマンド"]},{"code":401,"indent":0,"parameters":["「大丈夫か！支援する！」"]},{"code":335,"indent":0,"parameters":[2]},{"code":0,"indent":0,"parameters":[]}],"span":0}]},
{"id":4,"members":[{"enemyId":100,"x":216,"y":444,"hidden":false}],"name":"陸戦型ノアタイタン","pages":[{"conditions":{"actorHp":50,"actorId":1,"actorValid":false,"enemyHp":50,"enemyIndex":0,"enemyValid":false,"switchId":1,"switchValid":false,"turnA":0,"turnB":0,"turnEnding":false,"turnValid":false},"list":[{"code":0,"indent":0,"parameters":[]}],"span":0}]},
{"id":5,"members":[{"enemyId":5,"x":246,"y":415,"hidden":false}],"name":"オーク","pages":[{"conditions":{"actorHp":50,"actorId":1,"actorValid":false,"enemyHp":50,"enemyIndex":0,"enemyValid":false,"switchId":1,"switchValid":false,"turnA":0,"turnB":0,"turnEnding":false,"turnValid":false},"list":[{"code":0,"indent":0,"parameters":[]}],"span":0}]},
{"id":6,"members":[],"name":"","pages":[{"conditions":{"actorHp":50,"actorId":1,"actorValid":false,"enemyHp":50,"enemyIndex":0,"enemyValid":false,"switchId":1,"switchValid":false,"turnA":0,"turnB":0,"turnEnding":false,"turnValid":false},"list":[{"code":0,"indent":0,"parameters":[]}],"span":0}]},
{"id":7,"members":[{"enemyId":7,"x":198,"y":403,"hidden":false}],"name":"ミノタウロスLv53","pages":[{"conditions":{"actorHp":50,"actorId":1,"actorValid":false,"enemyHp":50,"enemyIndex":0,"enemyValid":false,"switchId":1,"switchValid":false,"turnA":0,"turnB":0,"turnEnding":false,"turnValid":false},"list":[{"code":0,"indent":0,"parameters":[]}],"span":0}]},
{"id":8,"members":[{"enemyId":9,"x":201,"y":403,"hidden":false}],"name":"劣化ミノタウロスLv53","pages":[{"conditions":{"actorHp":20,"actorId":1,"actorValid":true,"enemyHp":50,"enemyIndex":0,"enemyValid":false,"switchId":1,"switchValid":false,"turnA":0,"turnB":0,"turnEnding":true,"turnValid":false},"list":[{"code":101,"indent":0,"parameters":["",0,0,2]},{"code":401,"indent":0,"parameters":["\\C[4]seravin:\\C[0]"]},{"code":401,"indent":0,"parameters":["「Mananさん！これを使って！」"]},{"code":126,"indent":0,"parameters":[6,0,0,1]},{"code":101,"indent":0,"parameters":["",0,0,2]},{"code":401,"indent":0,"parameters":["\\I[176]ヒーリング ポーションを貰った！"]},{"code":0,"indent":0,"parameters":[]}],"span":0}]},
{"id":9,"members":[{"enemyId":8,"x":150,"y":340,"hidden":false}],"name":"ゲスナイト","pages":[{"conditions":{"actorHp":40,"actorId":1,"actorValid":true,"enemyHp":50,"enemyIndex":0,"enemyValid":false,"switchId":1,"switchValid":false,"turnA":2,"turnB":2,"turnEnding":true,"turnValid":false},"list":[{"code":337,"indent":0,"parameters":[0,43]},{"code":314,"indent":0,"parameters":[0,0]},{"code":356,"indent":0,"parameters":["EnemyBook add 8"]},{"code":0,"indent":0,"parameters":[]}],"span":0},{"conditions":{"actorHp":40,"actorId":1,"actorValid":true,"enemyHp":50,"enemyIndex":0,"enemyValid":false,"switchId":1,"switchValid":false,"turnA":2,"turnB":2,"turnEnding":true,"turnValid":false},"list":[{"code":337,"indent":0,"parameters":[0,43]},{"code":314,"indent":0,"parameters":[0,0]},{"code":356,"indent":0,"parameters":["EnemyBook add 8"]},{"code":0,"indent":0,"parameters":[]}],"span":1},{"conditions":{"actorHp":50,"actorId":1,"actorValid":false,"enemyHp":5,"enemyIndex":0,"enemyValid":true,"switchId":1,"switchValid":false,"turnA":0,"turnB":0,"turnEnding":true,"turnValid":false},"list":[{"code":339,"indent":0,"parameters":[0,0,6,-2]},{"code":356,"indent":0,"parameters":["EnemyBook add 8"]},{"code":0,"indent":0,"parameters":[]}],"span":0}]},
{"id":10,"members":[],"name":"--------------","pages":[{"conditions":{"actorHp":50,"actorId":1,"actorValid":false,"enemyHp":50,"enemyIndex":0,"enemyValid":false,"switchId":1,"switchValid":false,"turnA":0,"turnB":0,"turnEnding":false,"turnValid":false},"list":[{"code":0,"indent":0,"parameters":[]}],"span":0}]},
{"id":11,"members":[{"enemyId":11,"x":166,"y":313,"hidden":false},{"enemyId":11,"x":255,"y":424,"hidden":false}],"name":"ケイプスパイダー*2","pages":[{"conditions":{"actorHp":50,"actorId":1,"actorValid":false,"enemyHp":50,"enemyIndex":0,"enemyValid":false,"switchId":1,"switchValid":false,"turnA":0,"turnB":0,"turnEnding":false,"turnValid":true},"list":[{"code":356,"indent":0,"parameters":["EnemyBook add 11"]},{"code":0,"indent":0,"parameters":[]}],"span":1},{"conditions":{"actorHp":50,"actorId":1,"actorValid":false,"enemyHp":50,"enemyIndex":0,"enemyValid":false,"switchId":1,"switchValid":false,"turnA":1,"turnB":0,"turnEnding":false,"turnValid":true},"list":[{"code":0,"indent":0,"parameters":[]}],"span":0}]},
{"id":12,"members":[{"enemyId":12,"x":127,"y":406,"hidden":false},{"enemyId":12,"x":170,"y":322,"hidden":false},{"enemyId":11,"x":279,"y":370,"hidden":false}],"name":"こうもり*2, ケイプスパイダー","pages":[{"conditions":{"actorHp":50,"actorId":1,"actorValid":false,"enemyHp":50,"enemyIndex":0,"enemyValid":false,"switchId":1,"switchValid":false,"turnA":0,"turnB":0,"turnEnding":false,"turnValid":false},"list":[{"code":0,"indent":0,"parameters":[]}],"span":0},{"conditions":{"actorHp":50,"actorId":1,"actorValid":false,"enemyHp":50,"enemyIndex":0,"enemyValid":false,"switchId":1,"switchValid":false,"turnA":0,"turnB":0,"turnEnding":false,"turnValid":true},"list":[{"code":356,"indent":0,"parameters":["EnemyBook add 12"]},{"code":0,"indent":0,"parameters":[]}],"span":1}]},
{"id":13,"members":[{"enemyId":12,"x":151,"y":406,"hidden":false},{"enemyId":12,"x":191,"y":295,"hidden":false}],"name":"こうもり*2","pages":[{"conditions":{"actorHp":50,"actorId":1,"actorValid":false,"enemyHp":50,"enemyIndex":0,"enemyValid":false,"switchId":1,"switchValid":false,"turnA":0,"turnB":0,"turnEnding":false,"turnValid":false},"list":[{"code":0,"indent":0,"parameters":[]}],"span":0}]},
{"id":14,"members":[{"enemyId":13,"x":131,"y":382,"hidden":false},{"enemyId":13,"x":129,"y":250,"hidden":false},{"enemyId":13,"x":274,"y":292,"hidden":false}],"name":"ケイプ キラービー*3","pages":[{"conditions":{"actorHp":50,"actorId":1,"actorValid":false,"enemyHp":50,"enemyIndex":0,"enemyValid":false,"switchId":1,"switchValid":false,"turnA":0,"turnB":0,"turnEnding":false,"turnValid":true},"list":[{"code":356,"indent":0,"parameters":["EnemyBook add 13"]},{"code":0,"indent":0,"parameters":[]}],"span":1}]},
{"id":15,"members":[{"enemyId":14,"x":251,"y":349,"hidden":false},{"enemyId":13,"x":109,"y":370,"hidden":false},{"enemyId":13,"x":218,"y":250,"hidden":false}],"name":"リトル スコーピオン, ケイプ キラービー*2","pages":[{"conditions":{"actorHp":50,"actorId":1,"actorValid":false,"enemyHp":50,"enemyIndex":0,"enemyValid":false,"switchId":1,"switchValid":false,"turnA":0,"turnB":0,"turnEnding":false,"turnValid":false},"list":[{"code":0,"indent":0,"parameters":[]}],"span":0},{"conditions":{"actorHp":50,"actorId":1,"actorValid":false,"enemyHp":50,"enemyIndex":0,"enemyValid":false,"switchId":1,"switchValid":false,"turnA":0,"turnB":0,"turnEnding":false,"turnValid":true},"list":[{"code":356,"indent":0,"parameters":["EnemyBook add 13"]},{"code":356,"indent":0,"parameters":["EnemyBook add 14"]},{"code":0,"indent":0,"parameters":[]}],"span":1}]},
{"id":16,"members":[{"enemyId":13,"x":156,"y":313,"hidden":false}],"name":"チュートリアル ビー","pages":[{"conditions":{"actorHp":50,"actorId":1,"actorValid":false,"enemyHp":50,"enemyIndex":0,"enemyValid":false,"switchId":1,"switchValid":false,"turnA":0,"turnB":0,"turnEnding":false,"turnValid":true},"list":[{"code":331,"indent":0,"parameters":[-1,1,0,50,false]},{"code":333,"indent":0,"parameters":[0,0,5]},{"code":0,"indent":0,"parameters":[]}],"span":0}]},
{"id":17,"members":[{"enemyId":12,"x":76,"y":403,"hidden":false},{"enemyId":12,"x":158,"y":241,"hidden":false},{"enemyId":12,"x":258,"y":361,"hidden":false}],"name":"こうもり*3","pages":[{"conditions":{"actorHp":50,"actorId":1,"actorValid":false,"enemyHp":50,"enemyIndex":0,"enemyValid":false,"switchId":1,"switchValid":false,"turnA":0,"turnB":0,"turnEnding":false,"turnValid":false},"list":[{"code":0,"indent":0,"parameters":[]}],"span":0}]},
{"id":18,"members":[{"enemyId":13,"x":224,"y":346,"hidden":false},{"enemyId":12,"x":68,"y":391,"hidden":false},{"enemyId":12,"x":132,"y":253,"hidden":false}],"name":"ケイプ キラービー, こうもり*2","pages":[{"conditions":{"actorHp":50,"actorId":1,"actorValid":false,"enemyHp":50,"enemyIndex":0,"enemyValid":false,"switchId":1,"switchValid":false,"turnA":0,"turnB":0,"turnEnding":false,"turnValid":false},"list":[{"code":0,"indent":0,"parameters":[]}],"span":0}]},
{"id":19,"members":[{"enemyId":15,"x":153,"y":355,"hidden":false}],"name":"シャークシオン","pages":[{"conditions":{"actorHp":50,"actorId":1,"actorValid":false,"enemyHp":50,"enemyIndex":0,"enemyValid":false,"switchId":1,"switchValid":false,"turnA":0,"turnB":0,"turnEnding":false,"turnValid":false},"list":[{"code":0,"indent":0,"parameters":[]}],"span":0},{"conditions":{"actorHp":50,"actorId":1,"actorValid":false,"enemyHp":50,"enemyIndex":0,"enemyValid":false,"switchId":1,"switchValid":false,"turnA":0,"turnB":0,"turnEnding":false,"turnValid":true},"list":[{"code":356,"indent":0,"parameters":["EnemyBook add 15"]},{"code":0,"indent":0,"parameters":[]}],"span":0}]},
{"id":20,"members":[{"enemyId":15,"x":94,"y":412,"hidden":false},{"enemyId":15,"x":191,"y":265,"hidden":false}],"name":"シャークシオン*2","pages":[{"conditions":{"actorHp":50,"actorId":1,"actorValid":false,"enemyHp":50,"enemyIndex":0,"enemyValid":false,"switchId":1,"switchValid":false,"turnA":0,"turnB":0,"turnEnding":false,"turnValid":true},"list":[{"code":356,"indent":0,"parameters":["EnemyBook add 13"]},{"code":0,"indent":0,"parameters":[]}],"span":1}]},
{"id":21,"members":[{"enemyId":16,"x":150,"y":364,"hidden":false}],"name":"先行オーク","pages":[{"conditions":{"actorHp":50,"actorId":1,"actorValid":false,"enemyHp":50,"enemyIndex":0,"enemyValid":false,"switchId":1,"switchValid":false,"turnA":0,"turnB":0,"turnEnding":false,"turnValid":true},"list":[{"code":356,"indent":0,"parameters":["EnemyBook add 14"]},{"code":0,"indent":0,"parameters":[]}],"span":1}]},
{"id":22,"members":[{"enemyId":17,"x":231,"y":436,"hidden":false}],"name":"ブルーオーク ガイ","pages":[{"conditions":{"actorHp":50,"actorId":1,"actorValid":false,"enemyHp":50,"enemyIndex":0,"enemyValid":false,"switchId":1,"switchValid":false,"turnA":0,"turnB":0,"turnEnding":false,"turnValid":false},"list":[{"code":0,"indent":0,"parameters":[]}],"span":0},{"conditions":{"actorHp":50,"actorId":1,"actorValid":false,"enemyHp":50,"enemyIndex":0,"enemyValid":false,"switchId":1,"switchValid":false,"turnA":0,"turnB":0,"turnEnding":false,"turnValid":true},"list":[{"code":356,"indent":0,"parameters":["EnemyBook add 15"]},{"code":0,"indent":0,"parameters":[]}],"span":1}]},
{"id":23,"members":[{"enemyId":14,"x":186,"y":310,"hidden":false}],"name":"level1 Little boss","pages":[{"conditions":{"actorHp":50,"actorId":1,"actorValid":false,"enemyHp":50,"enemyIndex":0,"enemyValid":false,"switchId":1,"switchValid":false,"turnA":0,"turnB":0,"turnEnding":false,"turnValid":true},"list":[{"code":313,"indent":0,"parameters":[0,0,0,53]},{"code":333,"indent":0,"parameters":[0,0,52]},{"code":331,"indent":0,"parameters":[-1,0,0,9999,false]},{"code":356,"indent":0,"parameters":["EnemyBook add 14"]},{"code":0,"indent":0,"parameters":[]}],"span":0}]},
{"id":24,"members":[{"enemyId":13,"x":180,"y":310,"hidden":false},{"enemyId":12,"x":126,"y":421,"hidden":false},{"enemyId":12,"x":294,"y":304,"hidden":false}],"name":"level2 Little boss","pages":[{"conditions":{"actorHp":50,"actorId":1,"actorValid":false,"enemyHp":50,"enemyIndex":0,"enemyValid":false,"switchId":1,"switchValid":false,"turnA":0,"turnB":0,"turnEnding":false,"turnValid":true},"list":[{"code":313,"indent":0,"parameters":[0,0,0,53]},{"code":333,"indent":0,"parameters":[0,0,52]},{"code":331,"indent":0,"parameters":[-1,0,0,9999,false]},{"code":356,"indent":0,"parameters":["EnemyBook add 12"]},{"code":356,"indent":0,"parameters":["EnemyBook add 13"]},{"code":0,"indent":0,"parameters":[]}],"span":0}]},
{"id":25,"members":[{"enemyId":15,"x":225,"y":340,"hidden":false}],"name":"level3 Little boss","pages":[{"conditions":{"actorHp":50,"actorId":1,"actorValid":false,"enemyHp":50,"enemyIndex":0,"enemyValid":false,"switchId":1,"switchValid":false,"turnA":0,"turnB":0,"turnEnding":false,"turnValid":true},"list":[{"code":313,"indent":0,"parameters":[0,0,0,53]},{"code":333,"indent":0,"parameters":[0,0,52]},{"code":331,"indent":0,"parameters":[-1,0,0,9999,false]},{"code":356,"indent":0,"parameters":["EnemyBook add 13"]},{"code":0,"indent":0,"parameters":[]}],"span":0}]},
{"id":26,"members":[{"enemyId":16,"x":219,"y":367,"hidden":false}],"name":"level4 Little boss","pages":[{"conditions":{"actorHp":50,"actorId":1,"actorValid":false,"enemyHp":50,"enemyIndex":0,"enemyValid":false,"switchId":1,"switchValid":false,"turnA":0,"turnB":0,"turnEnding":false,"turnValid":true},"list":[{"code":313,"indent":0,"parameters":[0,0,0,53]},{"code":333,"indent":0,"parameters":[0,0,52]},{"code":331,"indent":0,"parameters":[-1,0,0,9999,false]},{"code":356,"indent":0,"parameters":["EnemyBook add 14"]},{"code":0,"indent":0,"parameters":[]}],"span":0}]},
{"id":27,"members":[{"enemyId":16,"x":147,"y":439,"hidden":false},{"enemyId":16,"x":342,"y":322,"hidden":false}],"name":"level5 Little boss","pages":[{"conditions":{"actorHp":50,"actorId":1,"actorValid":false,"enemyHp":50,"enemyIndex":0,"enemyValid":false,"switchId":1,"switchValid":false,"turnA":0,"turnB":0,"turnEnding":false,"turnValid":true},"list":[{"code":313,"indent":0,"parameters":[0,0,0,53]},{"code":333,"indent":0,"parameters":[-1,0,52]},{"code":331,"indent":0,"parameters":[-1,0,0,9999,false]},{"code":356,"indent":0,"parameters":["EnemyBook add 14"]},{"code":0,"indent":0,"parameters":[]}],"span":0}]},
{"id":28,"members":[],"name":"--------------","pages":[{"conditions":{"actorHp":50,"actorId":1,"actorValid":false,"enemyHp":50,"enemyIndex":0,"enemyValid":false,"switchId":1,"switchValid":false,"turnA":0,"turnB":0,"turnEnding":false,"turnValid":false},"list":[{"code":0,"indent":0,"parameters":[]}],"span":0}]},
{"id":29,"members":[{"enemyId":63,"x":120,"y":337,"hidden":false},{"enemyId":64,"x":357,"y":406,"hidden":true},{"enemyId":64,"x":93,"y":424,"hidden":true},{"enemyId":64,"x":297,"y":286,"hidden":true},{"enemyId":64,"x":243,"y":442,"hidden":true},{"enemyId":64,"x":387,"y":322,"hidden":true}],"name":"三首ケルベロス","pages":[{"conditions":{"actorHp":50,"actorId":1,"actorValid":false,"enemyHp":50,"enemyIndex":0,"enemyValid":false,"switchId":1,"switchValid":false,"turnA":0,"turnB":0,"turnEnding":false,"turnValid":true},"list":[{"code":356,"indent":0,"parameters":["EnemyBook add 63"]},{"code":326,"indent":0,"parameters":[0,0,0,0,100]},{"code":0,"indent":0,"parameters":[]}],"span":0},{"conditions":{"actorHp":50,"actorId":1,"actorValid":false,"enemyHp":70,"enemyIndex":0,"enemyValid":false,"switchId":1,"switchValid":false,"turnA":6,"turnB":6,"turnEnding":true,"turnValid":true},"list":[{"code":129,"indent":0,"parameters":[6,0,false]},{"code":129,"indent":0,"parameters":[12,0,false]},{"code":121,"indent":0,"parameters":[64,64,0]},{"code":101,"indent":0,"parameters":["",0,0,2]},{"code":401,"indent":0,"parameters":["\\C[4]riche:\\C[0]"]},{"code":401,"indent":0,"parameters":["「Mananさん！援護します！」"]},{"code":101,"indent":0,"parameters":["",0,0,2]},{"code":401,"indent":0,"parameters":["\\C[4]Manan:\\C[0]"]},{"code":401,"indent":0,"parameters":["「richeさん！」"]},{"code":101,"indent":0,"parameters":["",0,0,2]},{"code":401,"indent":0,"parameters":["\\C[4]ノレイス:\\C[0]"]},{"code":401,"indent":0,"parameters":["「遅れてごめんさない、予想以上に迷っちゃって」"]},{"code":101,"indent":0,"parameters":["",0,0,2]},{"code":401,"indent":0,"parameters":["\\C[4]Manan:\\C[0]"]},{"code":401,"indent":0,"parameters":["「ノレさん！」"]},{"code":101,"indent":0,"parameters":["",0,0,2]},{"code":401,"indent":0,"parameters":["\\C[4]ノレイス:\\C[0]"]},{"code":401,"indent":0,"parameters":["「話は後で、まずはこの敵を片付けましょう！」"]},{"code":101,"indent":0,"parameters":["",0,0,2]},{"code":401,"indent":0,"parameters":["\\C[4]Manan:\\C[0]"]},{"code":401,"indent":0,"parameters":["「はい！」"]},{"code":101,"indent":0,"parameters":["",0,0,1]},{"code":401,"indent":0,"parameters":["         Mananはいくつかの\\c[2]アイテム\\c[0]を分けてもらった！"]},{"code":126,"indent":0,"parameters":[7,0,0,5]},{"code":126,"indent":0,"parameters":[9,0,0,5]},{"code":126,"indent":0,"parameters":[11,0,0,5]},{"code":126,"indent":0,"parameters":[12,0,0,5]},{"code":126,"indent":0,"parameters":[14,0,0,5]},{"code":326,"indent":0,"parameters":[0,0,0,0,100]},{"code":224,"indent":0,"parameters":[[255,255,255,170],60,false]},{"code":241,"indent":0,"parameters":[{"name":"Battle2","volume":90,"pitch":100,"pan":0}]},{"code":314,"indent":0,"parameters":[0,0]},{"code":250,"indent":0,"parameters":[{"name":"Barrier","volume":90,"pitch":100,"pan":0}]},{"code":313,"indent":0,"parameters":[0,0,0,37]},{"code":0,"indent":0,"parameters":[]}],"span":0},{"conditions":{"actorHp":50,"actorId":1,"actorValid":false,"enemyHp":80,"enemyIndex":0,"enemyValid":true,"switchId":1,"switchValid":false,"turnA":5,"turnB":5,"turnEnding":false,"turnValid":false},"list":[{"code":337,"indent":0,"parameters":[0,37]},{"code":101,"indent":0,"parameters":["",0,1,1]},{"code":401,"indent":0,"parameters":["　　　　　　三首ケロベロスは仲間を呼んだ！"]},{"code":335,"indent":0,"parameters":[1]},{"code":335,"indent":0,"parameters":[2]},{"code":0,"indent":0,"parameters":[]}],"span":0},{"conditions":{"actorHp":50,"actorId":1,"actorValid":false,"enemyHp":60,"enemyIndex":0,"enemyValid":true,"switchId":1,"switchValid":false,"turnA":5,"turnB":5,"turnEnding":false,"turnValid":false},"list":[{"code":337,"indent":0,"parameters":[0,37]},{"code":101,"indent":0,"parameters":["",0,1,1]},{"code":401,"indent":0,"parameters":["　　　　　三首ケロベロスは再び仲間を呼んだ！"]},{"code":335,"indent":0,"parameters":[3]},{"code":335,"indent":0,"parameters":[4]},{"code":335,"indent":0,"parameters":[5]},{"code":0,"indent":0,"parameters":[]}],"span":0}]},
{"id":30,"members":[{"enemyId":72,"x":102,"y":391,"hidden":false},{"enemyId":73,"x":279,"y":394,"hidden":true}],"name":"ダークアリスベル","pages":[{"conditions":{"actorHp":50,"actorId":1,"actorValid":false,"enemyHp":50,"enemyIndex":0,"enemyValid":false,"switchId":1,"switchValid":false,"turnA":2,"turnB":2,"turnEnding":false,"turnValid":true},"list":[{"code":335,"indent":0,"parameters":[1]},{"code":337,"indent":0,"parameters":[1,57]},{"code":333,"indent":0,"parameters":[0,0,60]},{"code":0,"indent":0,"parameters":[]}],"span":0},{"conditions":{"actorHp":50,"actorId":1,"actorValid":false,"enemyHp":0,"enemyIndex":1,"enemyValid":true,"switchId":1,"switchValid":false,"turnA":0,"turnB":0,"turnEnding":false,"turnValid":false},"list":[{"code":333,"indent":0,"parameters":[0,1,60]},{"code":0,"indent":0,"parameters":[]}],"span":0}]},
{"id":31,"members":[{"enemyId":85,"x":120,"y":337,"hidden":false},{"enemyId":86,"x":90,"y":388,"hidden":true},{"enemyId":86,"x":357,"y":403,"hidden":true},{"enemyId":86,"x":204,"y":435,"hidden":true},{"enemyId":86,"x":375,"y":310,"hidden":true},{"enemyId":86,"x":285,"y":271,"hidden":true}],"name":"追憶の三首ケルベロス","pages":[{"conditions":{"actorHp":50,"actorId":1,"actorValid":false,"enemyHp":50,"enemyIndex":0,"enemyValid":false,"switchId":1,"switchValid":false,"turnA":0,"turnB":0,"turnEnding":false,"turnValid":true},"list":[{"code":326,"indent":0,"parameters":[0,0,0,0,100]},{"code":0,"indent":0,"parameters":[]}],"span":0},{"conditions":{"actorHp":50,"actorId":1,"actorValid":false,"enemyHp":80,"enemyIndex":0,"enemyValid":true,"switchId":1,"switchValid":false,"turnA":5,"turnB":5,"turnEnding":false,"turnValid":false},"list":[{"code":337,"indent":0,"parameters":[0,37]},{"code":101,"indent":0,"parameters":["",0,1,1]},{"code":401,"indent":0,"parameters":["　　　　　　三首ケロベロスは仲間を呼んだ！"]},{"code":335,"indent":0,"parameters":[1]},{"code":335,"indent":0,"parameters":[2]},{"code":0,"indent":0,"parameters":[]}],"span":0},{"conditions":{"actorHp":50,"actorId":1,"actorValid":false,"enemyHp":60,"enemyIndex":0,"enemyValid":true,"switchId":1,"switchValid":false,"turnA":5,"turnB":5,"turnEnding":false,"turnValid":false},"list":[{"code":311,"indent":0,"parameters":[0,0,0,0,50,false]},{"code":326,"indent":0,"parameters":[0,0,0,0,50]},{"code":337,"indent":0,"parameters":[0,37]},{"code":101,"indent":0,"parameters":["",0,1,1]},{"code":401,"indent":0,"parameters":["　　　　　三首ケロベロスは再び仲間を呼んだ！"]},{"code":335,"indent":0,"parameters":[3]},{"code":335,"indent":0,"parameters":[4]},{"code":335,"indent":0,"parameters":[5]},{"code":0,"indent":0,"parameters":[]}],"span":0}]},
{"id":32,"members":[],"name":"--------------","pages":[{"conditions":{"actorHp":50,"actorId":1,"actorValid":false,"enemyHp":50,"enemyIndex":0,"enemyValid":false,"switchId":1,"switchValid":false,"turnA":0,"turnB":0,"turnEnding":false,"turnValid":false},"list":[{"code":0,"indent":0,"parameters":[]}],"span":0}]},
{"id":33,"members":[{"enemyId":65,"x":225,"y":428,"hidden":false}],"name":"ヤマファンゴ","pages":[{"conditions":{"actorHp":50,"actorId":1,"actorValid":false,"enemyHp":50,"enemyIndex":0,"enemyValid":false,"switchId":1,"switchValid":false,"turnA":1,"turnB":1,"turnEnding":true,"turnValid":true},"list":[{"code":129,"indent":0,"parameters":[7,0,false]},{"code":129,"indent":0,"parameters":[8,0,false]},{"code":314,"indent":0,"parameters":[0,0]},{"code":313,"indent":0,"parameters":[0,0,0,22]},{"code":313,"indent":0,"parameters":[0,0,0,23]},{"code":313,"indent":0,"parameters":[0,0,0,54]},{"code":337,"indent":0,"parameters":[0,43]},{"code":0,"indent":0,"parameters":[]}],"span":0}]},
{"id":34,"members":[{"enemyId":74,"x":120,"y":376,"hidden":false}],"name":"yukiss","pages":[{"conditions":{"actorHp":50,"actorId":1,"actorValid":false,"enemyHp":50,"enemyIndex":0,"enemyValid":false,"switchId":1,"switchValid":false,"turnA":0,"turnB":0,"turnEnding":false,"turnValid":false},"list":[{"code":0,"indent":0,"parameters":[]}],"span":0}]},
{"id":35,"members":[],"name":"","pages":[{"conditions":{"actorHp":50,"actorId":1,"actorValid":false,"enemyHp":50,"enemyIndex":0,"enemyValid":false,"switchId":1,"switchValid":false,"turnA":0,"turnB":0,"turnEnding":false,"turnValid":false},"list":[{"code":0,"indent":0,"parameters":[]}],"span":0}]},
{"id":36,"members":[],"name":"--------------","pages":[{"conditions":{"actorHp":50,"actorId":1,"actorValid":false,"enemyHp":50,"enemyIndex":0,"enemyValid":false,"switchId":1,"switchValid":false,"turnA":0,"turnB":0,"turnEnding":false,"turnValid":false},"list":[{"code":0,"indent":0,"parameters":[]}],"span":0}]},
{"id":37,"members":[{"enemyId":25,"x":165,"y":418,"hidden":false}],"name":"ヘビーギガース","pages":[{"conditions":{"actorHp":50,"actorId":1,"actorValid":false,"enemyHp":50,"enemyIndex":0,"enemyValid":false,"switchId":1,"switchValid":false,"turnA":0,"turnB":0,"turnEnding":false,"turnValid":false},"list":[{"code":0,"indent":0,"parameters":[]}],"span":0}]},
{"id":38,"members":[],"name":"","pages":[{"conditions":{"actorHp":50,"actorId":1,"actorValid":false,"enemyHp":50,"enemyIndex":0,"enemyValid":false,"switchId":1,"switchValid":false,"turnA":0,"turnB":0,"turnEnding":false,"turnValid":false},"list":[{"code":0,"indent":0,"parameters":[]}],"span":0}]},
{"id":39,"members":[],"name":"","pages":[{"conditions":{"actorHp":50,"actorId":1,"actorValid":false,"enemyHp":50,"enemyIndex":0,"enemyValid":false,"switchId":1,"switchValid":false,"turnA":0,"turnB":0,"turnEnding":false,"turnValid":false},"list":[{"code":0,"indent":0,"parameters":[]}],"span":0}]},
{"id":40,"members":[],"name":"","pages":[{"conditions":{"actorHp":50,"actorId":1,"actorValid":false,"enemyHp":50,"enemyIndex":0,"enemyValid":false,"switchId":1,"switchValid":false,"turnA":0,"turnB":0,"turnEnding":false,"turnValid":false},"list":[{"code":0,"indent":0,"parameters":[]}],"span":0}]},
{"id":41,"members":[],"name":"","pages":[{"conditions":{"actorHp":50,"actorId":1,"actorValid":false,"enemyHp":50,"enemyIndex":0,"enemyValid":false,"switchId":1,"switchValid":false,"turnA":0,"turnB":0,"turnEnding":false,"turnValid":false},"list":[{"code":0,"indent":0,"parameters":[]}],"span":0}]},
{"id":42,"members":[],"name":"--------------","pages":[{"conditions":{"actorHp":50,"actorId":1,"actorValid":false,"enemyHp":50,"enemyIndex":0,"enemyValid":false,"switchId":1,"switchValid":false,"turnA":0,"turnB":0,"turnEnding":false,"turnValid":false},"list":[{"code":0,"indent":0,"parameters":[]}],"span":0}]},
{"id":43,"members":[{"enemyId":81,"x":96,"y":334,"hidden":false},{"enemyId":81,"x":285,"y":358,"hidden":false},{"enemyId":81,"x":81,"y":436,"hidden":false},{"enemyId":81,"x":210,"y":444,"hidden":false},{"enemyId":81,"x":201,"y":295,"hidden":false}],"name":"フェアリー*5","pages":[{"conditions":{"actorHp":50,"actorId":1,"actorValid":false,"enemyHp":50,"enemyIndex":0,"enemyValid":false,"switchId":1,"switchValid":false,"turnA":0,"turnB":0,"turnEnding":false,"turnValid":true},"list":[{"code":326,"indent":0,"parameters":[0,0,0,0,99]},{"code":0,"indent":0,"parameters":[]}],"span":0}]},
{"id":44,"members":[{"enemyId":83,"x":138,"y":444,"hidden":false}],"name":"マッスル オブ ザ キャット","pages":[{"conditions":{"actorHp":50,"actorId":1,"actorValid":false,"enemyHp":50,"enemyIndex":0,"enemyValid":false,"switchId":1,"switchValid":false,"turnA":3,"turnB":3,"turnEnding":false,"turnValid":true},"list":[{"code":101,"indent":0,"parameters":["",0,0,2]},{"code":401,"indent":0,"parameters":["\\C[4]ネコさん:\\C[0]"]},{"code":401,"indent":0,"parameters":["「ニャニャ、マッスルボティのネコさんにはそんなの"]},{"code":401,"indent":0,"parameters":["　効かないニャ」"]},{"code":0,"indent":0,"parameters":[]}],"span":0},{"conditions":{"actorHp":50,"actorId":1,"actorValid":false,"enemyHp":50,"enemyIndex":0,"enemyValid":false,"switchId":1,"switchValid":false,"turnA":5,"turnB":5,"turnEnding":false,"turnValid":true},"list":[{"code":101,"indent":0,"parameters":["",0,0,2]},{"code":401,"indent":0,"parameters":["\\C[4]ネコさん:\\C[0]"]},{"code":401,"indent":0,"parameters":["「ふっふ～」"]},{"code":0,"indent":0,"parameters":[]}],"span":0},{"conditions":{"actorHp":50,"actorId":1,"actorValid":false,"enemyHp":50,"enemyIndex":0,"enemyValid":false,"switchId":1,"switchValid":false,"turnA":8,"turnB":8,"turnEnding":false,"turnValid":true},"list":[{"code":101,"indent":0,"parameters":["",0,0,2]},{"code":401,"indent":0,"parameters":["\\C[4]ネコさん:\\C[0]"]},{"code":401,"indent":0,"parameters":["「これでとどめを刺すニャ！」"]},{"code":337,"indent":0,"parameters":[0,53]},{"code":230,"indent":0,"parameters":[25]},{"code":337,"indent":0,"parameters":[0,117]},{"code":230,"indent":0,"parameters":[30]},{"code":337,"indent":0,"parameters":[0,132]},{"code":101,"indent":0,"parameters":["",0,0,2]},{"code":401,"indent":0,"parameters":["\\C[4]ネコさん:\\C[0]"]},{"code":401,"indent":0,"parameters":["「うにゃ！？」"]},{"code":129,"indent":0,"parameters":[14,0,false]},{"code":101,"indent":0,"parameters":["",0,0,2]},{"code":401,"indent":0,"parameters":["\\C[4]？？？:\\C[0]"]},{"code":401,"indent":0,"parameters":["「何をしているの？」"]},{"code":101,"indent":0,"parameters":["",0,0,2]},{"code":401,"indent":0,"parameters":["\\C[4]ネコさん:\\C[0]"]},{"code":401,"indent":0,"parameters":["「にゃにゃ…シロカミサン…」"]},{"code":101,"indent":0,"parameters":["sirokami",4,0,2]},{"code":401,"indent":0,"parameters":["\\C[4]シロカミ:\\C[0]"]},{"code":401,"indent":0,"parameters":["「体験版だからって参加権は貴方にはないのよ？」"]},{"code":101,"indent":0,"parameters":["",0,0,2]},{"code":401,"indent":0,"parameters":["\\C[4]ネコさん:\\C[0]"]},{"code":401,"indent":0,"parameters":["「僕はブログで収まる器じゃないんだニャ！」"]},{"code":101,"indent":0,"parameters":["sirokami",4,0,2]},{"code":401,"indent":0,"parameters":["\\C[4]シロカミ:\\C[0]"]},{"code":401,"indent":0,"parameters":["「それがあなたの考え？」"]},{"code":101,"indent":0,"parameters":["",0,0,2]},{"code":401,"indent":0,"parameters":["\\C[4]ネコさん:\\C[0]"]},{"code":401,"indent":0,"parameters":["「ニャ！」"]},{"code":101,"indent":0,"parameters":["sirokami",4,0,2]},{"code":401,"indent":0,"parameters":["\\C[4]シロカミ:\\C[0]"]},{"code":401,"indent":0,"parameters":["「・・・」"]},{"code":101,"indent":0,"parameters":["",0,0,2]},{"code":401,"indent":0,"parameters":["\\C[4]ネコさん:\\C[0]"]},{"code":401,"indent":0,"parameters":["「に・・・にゃ？」"]},{"code":101,"indent":0,"parameters":["sirokami",4,0,2]},{"code":401,"indent":0,"parameters":["\\C[4]シロカミ:\\C[0]"]},{"code":401,"indent":0,"parameters":["「\\c[2]\\{焦げ饅頭にしてあげる\\c[0]」"]},{"code":101,"indent":0,"parameters":["",0,0,2]},{"code":401,"indent":0,"parameters":["\\C[4]ネコさん:\\C[0]"]},{"code":401,"indent":0,"parameters":["「ミギャー！！」"]},{"code":0,"indent":0,"parameters":[]}],"span":0},{"conditions":{"actorHp":50,"actorId":1,"actorValid":false,"enemyHp":50,"enemyIndex":0,"enemyValid":false,"switchId":1,"switchValid":false,"turnA":16,"turnB":16,"turnEnding":false,"turnValid":true},"list":[{"code":101,"indent":0,"parameters":["sirokami",4,0,2]},{"code":401,"indent":0,"parameters":["\\C[4]シロカミ:\\C[0]"]},{"code":401,"indent":0,"parameters":["「・・・貴方、少し力を貸して」"]},{"code":250,"indent":0,"parameters":[{"name":"Ice12","volume":90,"pitch":100,"pan":0}]},{"code":314,"indent":0,"parameters":[0,0]},{"code":129,"indent":0,"parameters":[1,1,false]},{"code":250,"indent":0,"parameters":[{"name":"Raise1","volume":90,"pitch":100,"pan":0}]},{"code":224,"indent":0,"parameters":[[255,255,255,170],60,true]},{"code":129,"indent":0,"parameters":[22,0,false]},{"code":241,"indent":0,"parameters":[{"name":"VictoryLoop1","volume":90,"pitch":100,"pan":0}]},{"code":0,"indent":0,"parameters":[]}],"span":0}]},
{"id":45,"members":[],"name":"------山--------","pages":[{"conditions":{"actorHp":50,"actorId":1,"actorValid":false,"enemyHp":50,"enemyIndex":0,"enemyValid":false,"switchId":1,"switchValid":false,"turnA":0,"turnB":0,"turnEnding":false,"turnValid":false},"list":[{"code":0,"indent":0,"parameters":[]}],"span":0}]},
{"id":46,"members":[{"enemyId":19,"x":316,"y":412,"hidden":false},{"enemyId":19,"x":213,"y":280,"hidden":false}],"name":"マウンテン ラット*2","pages":[{"conditions":{"actorHp":50,"actorId":1,"actorValid":false,"enemyHp":50,"enemyIndex":0,"enemyValid":false,"switchId":1,"switchValid":false,"turnA":0,"turnB":0,"turnEnding":false,"turnValid":false},"list":[{"code":0,"indent":0,"parameters":[]}],"span":0}]},
{"id":47,"members":[{"enemyId":19,"x":221,"y":436,"hidden":false},{"enemyId":19,"x":301,"y":307,"hidden":false},{"enemyId":20,"x":131,"y":373,"hidden":false}],"name":"マウンテン ラット*2, オーク ディフェンス","pages":[{"conditions":{"actorHp":50,"actorId":1,"actorValid":false,"enemyHp":50,"enemyIndex":0,"enemyValid":false,"switchId":1,"switchValid":false,"turnA":0,"turnB":0,"turnEnding":false,"turnValid":false},"list":[{"code":0,"indent":0,"parameters":[]}],"span":0}]},
{"id":48,"members":[{"enemyId":20,"x":175,"y":430,"hidden":false},{"enemyId":20,"x":323,"y":280,"hidden":false}],"name":"オーク ディフェンス*2","pages":[{"conditions":{"actorHp":50,"actorId":1,"actorValid":false,"enemyHp":50,"enemyIndex":0,"enemyValid":false,"switchId":1,"switchValid":false,"turnA":0,"turnB":0,"turnEnding":false,"turnValid":false},"list":[{"code":0,"indent":0,"parameters":[]}],"span":0}]},
{"id":49,"members":[{"enemyId":13,"x":131,"y":382,"hidden":false},{"enemyId":13,"x":129,"y":250,"hidden":false},{"enemyId":13,"x":274,"y":292,"hidden":false}],"name":"ケイプ キラービー*3","pages":[{"conditions":{"actorHp":50,"actorId":1,"actorValid":false,"enemyHp":50,"enemyIndex":0,"enemyValid":false,"switchId":1,"switchValid":false,"turnA":0,"turnB":0,"turnEnding":false,"turnValid":false},"list":[{"code":0,"indent":0,"parameters":[]}],"span":0}]},
{"id":50,"members":[{"enemyId":14,"x":251,"y":349,"hidden":false},{"enemyId":13,"x":109,"y":370,"hidden":false},{"enemyId":13,"x":218,"y":250,"hidden":false}],"name":"リトル スコーピオン, ケイプ キラービー*2","pages":[{"conditions":{"actorHp":50,"actorId":1,"actorValid":false,"enemyHp":50,"enemyIndex":0,"enemyValid":false,"switchId":1,"switchValid":false,"turnA":0,"turnB":0,"turnEnding":false,"turnValid":false},"list":[{"code":0,"indent":0,"parameters":[]}],"span":0}]},
{"id":51,"members":[{"enemyId":13,"x":156,"y":313,"hidden":false}],"name":"チュートリアル ビー","pages":[{"conditions":{"actorHp":50,"actorId":1,"actorValid":false,"enemyHp":50,"enemyIndex":0,"enemyValid":false,"switchId":1,"switchValid":false,"turnA":0,"turnB":0,"turnEnding":false,"turnValid":true},"list":[{"code":331,"indent":0,"parameters":[-1,1,0,50,false]},{"code":333,"indent":0,"parameters":[0,0,5]},{"code":0,"indent":0,"parameters":[]}],"span":0}]},
{"id":52,"members":[{"enemyId":12,"x":76,"y":403,"hidden":false},{"enemyId":12,"x":158,"y":241,"hidden":false},{"enemyId":12,"x":258,"y":361,"hidden":false}],"name":"こうもり*3","pages":[{"conditions":{"actorHp":50,"actorId":1,"actorValid":false,"enemyHp":50,"enemyIndex":0,"enemyValid":false,"switchId":1,"switchValid":false,"turnA":0,"turnB":0,"turnEnding":false,"turnValid":false},"list":[{"code":0,"indent":0,"parameters":[]}],"span":0}]},
{"id":53,"members":[{"enemyId":13,"x":224,"y":346,"hidden":false},{"enemyId":12,"x":68,"y":391,"hidden":false},{"enemyId":12,"x":132,"y":253,"hidden":false}],"name":"ケイプ キラービー, こうもり*2","pages":[{"conditions":{"actorHp":50,"actorId":1,"actorValid":false,"enemyHp":50,"enemyIndex":0,"enemyValid":false,"switchId":1,"switchValid":false,"turnA":0,"turnB":0,"turnEnding":false,"turnValid":false},"list":[{"code":0,"indent":0,"parameters":[]}],"span":0}]},
{"id":54,"members":[{"enemyId":15,"x":153,"y":355,"hidden":false}],"name":"シャークシオン","pages":[{"conditions":{"actorHp":50,"actorId":1,"actorValid":false,"enemyHp":50,"enemyIndex":0,"enemyValid":false,"switchId":1,"switchValid":false,"turnA":0,"turnB":0,"turnEnding":false,"turnValid":false},"list":[{"code":0,"indent":0,"parameters":[]}],"span":0}]},
{"id":55,"members":[{"enemyId":15,"x":94,"y":412,"hidden":false},{"enemyId":15,"x":191,"y":265,"hidden":false}],"name":"シャークシオン*2","pages":[{"conditions":{"actorHp":50,"actorId":1,"actorValid":false,"enemyHp":50,"enemyIndex":0,"enemyValid":false,"switchId":1,"switchValid":false,"turnA":0,"turnB":0,"turnEnding":false,"turnValid":false},"list":[{"code":0,"indent":0,"parameters":[]}],"span":0}]},
{"id":56,"members":[{"enemyId":16,"x":150,"y":364,"hidden":false}],"name":"先行オーク","pages":[{"conditions":{"actorHp":50,"actorId":1,"actorValid":false,"enemyHp":50,"enemyIndex":0,"enemyValid":false,"switchId":1,"switchValid":false,"turnA":0,"turnB":0,"turnEnding":false,"turnValid":false},"list":[{"code":0,"indent":0,"parameters":[]}],"span":0}]},
{"id":57,"members":[{"enemyId":17,"x":231,"y":436,"hidden":false}],"name":"ブルーオーク ガイ","pages":[{"conditions":{"actorHp":50,"actorId":1,"actorValid":false,"enemyHp":50,"enemyIndex":0,"enemyValid":false,"switchId":1,"switchValid":false,"turnA":0,"turnB":0,"turnEnding":false,"turnValid":false},"list":[{"code":0,"indent":0,"parameters":[]}],"span":0}]},
{"id":58,"members":[{"enemyId":14,"x":186,"y":310,"hidden":false}],"name":"level1 Little boss","pages":[{"conditions":{"actorHp":50,"actorId":1,"actorValid":false,"enemyHp":50,"enemyIndex":0,"enemyValid":false,"switchId":1,"switchValid":false,"turnA":0,"turnB":0,"turnEnding":false,"turnValid":true},"list":[{"code":313,"indent":0,"parameters":[0,0,0,53]},{"code":333,"indent":0,"parameters":[0,0,52]},{"code":331,"indent":0,"parameters":[-1,0,0,9999,false]},{"code":0,"indent":0,"parameters":[]}],"span":0}]},
{"id":59,"members":[{"enemyId":13,"x":180,"y":310,"hidden":false},{"enemyId":12,"x":126,"y":421,"hidden":false},{"enemyId":12,"x":294,"y":304,"hidden":false}],"name":"level2 Little boss","pages":[{"conditions":{"actorHp":50,"actorId":1,"actorValid":false,"enemyHp":50,"enemyIndex":0,"enemyValid":false,"switchId":1,"switchValid":false,"turnA":0,"turnB":0,"turnEnding":false,"turnValid":true},"list":[{"code":313,"indent":0,"parameters":[0,0,0,53]},{"code":333,"indent":0,"parameters":[0,0,52]},{"code":331,"indent":0,"parameters":[-1,0,0,9999,false]},{"code":0,"indent":0,"parameters":[]}],"span":0}]},
{"id":60,"members":[{"enemyId":15,"x":225,"y":340,"hidden":false}],"name":"level3 Little boss","pages":[{"conditions":{"actorHp":50,"actorId":1,"actorValid":false,"enemyHp":50,"enemyIndex":0,"enemyValid":false,"switchId":1,"switchValid":false,"turnA":0,"turnB":0,"turnEnding":false,"turnValid":true},"list":[{"code":313,"indent":0,"parameters":[0,0,0,53]},{"code":333,"indent":0,"parameters":[0,0,52]},{"code":331,"indent":0,"parameters":[-1,0,0,9999,false]},{"code":0,"indent":0,"parameters":[]}],"span":0}]},
{"id":61,"members":[{"enemyId":16,"x":219,"y":367,"hidden":false}],"name":"level4 Little boss","pages":[{"conditions":{"actorHp":50,"actorId":1,"actorValid":false,"enemyHp":50,"enemyIndex":0,"enemyValid":false,"switchId":1,"switchValid":false,"turnA":0,"turnB":0,"turnEnding":false,"turnValid":true},"list":[{"code":313,"indent":0,"parameters":[0,0,0,53]},{"code":333,"indent":0,"parameters":[0,0,52]},{"code":331,"indent":0,"parameters":[-1,0,0,9999,false]},{"code":0,"indent":0,"parameters":[]}],"span":0}]},
{"id":62,"members":[{"enemyId":16,"x":147,"y":439,"hidden":false},{"enemyId":16,"x":342,"y":322,"hidden":false}],"name":"level5 Little boss","pages":[{"conditions":{"actorHp":50,"actorId":1,"actorValid":false,"enemyHp":50,"enemyIndex":0,"enemyValid":false,"switchId":1,"switchValid":false,"turnA":0,"turnB":0,"turnEnding":false,"turnValid":true},"list":[{"code":313,"indent":0,"parameters":[0,0,0,53]},{"code":333,"indent":0,"parameters":[-1,0,52]},{"code":331,"indent":0,"parameters":[-1,0,0,9999,false]},{"code":0,"indent":0,"parameters":[]}],"span":0}]},
{"id":63,"members":[],"name":"--------------","pages":[{"conditions":{"actorHp":50,"actorId":1,"actorValid":false,"enemyHp":50,"enemyIndex":0,"enemyValid":false,"switchId":1,"switchValid":false,"turnA":0,"turnB":0,"turnEnding":false,"turnValid":false},"list":[{"code":0,"indent":0,"parameters":[]}],"span":0}]},
{"id":64,"members":[{"enemyId":63,"x":120,"y":337,"hidden":false},{"enemyId":64,"x":357,"y":406,"hidden":true},{"enemyId":64,"x":93,"y":424,"hidden":true},{"enemyId":64,"x":297,"y":286,"hidden":true},{"enemyId":64,"x":243,"y":442,"hidden":true},{"enemyId":64,"x":387,"y":322,"hidden":true}],"name":"三首ケルベロス","pages":[{"conditions":{"actorHp":50,"actorId":1,"actorValid":false,"enemyHp":50,"enemyIndex":0,"enemyValid":false,"switchId":1,"switchValid":false,"turnA":0,"turnB":0,"turnEnding":false,"turnValid":true},"list":[{"code":326,"indent":0,"parameters":[0,0,0,0,100]},{"code":0,"indent":0,"parameters":[]}],"span":0},{"conditions":{"actorHp":50,"actorId":1,"actorValid":false,"enemyHp":70,"enemyIndex":0,"enemyValid":false,"switchId":1,"switchValid":false,"turnA":6,"turnB":6,"turnEnding":true,"turnValid":true},"list":[{"code":129,"indent":0,"parameters":[6,0,false]},{"code":129,"indent":0,"parameters":[12,0,false]},{"code":121,"indent":0,"parameters":[64,64,0]},{"code":101,"indent":0,"parameters":["",0,0,2]},{"code":401,"indent":0,"parameters":["\\C[4]riche:\\C[0]"]},{"code":401,"indent":0,"parameters":["「Mananさん！援護します！」"]},{"code":101,"indent":0,"parameters":["",0,0,2]},{"code":401,"indent":0,"parameters":["\\C[4]Manan:\\C[0]"]},{"code":401,"indent":0,"parameters":["「richeさん！」"]},{"code":101,"indent":0,"parameters":["",0,0,2]},{"code":401,"indent":0,"parameters":["\\C[4]ノレイス:\\C[0]"]},{"code":401,"indent":0,"parameters":["「遅れてごめんさない、予想以上に迷っちゃって」"]},{"code":101,"indent":0,"parameters":["",0,0,2]},{"code":401,"indent":0,"parameters":["\\C[4]Manan:\\C[0]"]},{"code":401,"indent":0,"parameters":["「ノレさん！」"]},{"code":101,"indent":0,"parameters":["",0,0,2]},{"code":401,"indent":0,"parameters":["\\C[4]ノレイス:\\C[0]"]},{"code":401,"indent":0,"parameters":["「話は後で、まずはこの敵を片付けましょう！」"]},{"code":101,"indent":0,"parameters":["",0,0,2]},{"code":401,"indent":0,"parameters":["\\C[4]Manan:\\C[0]"]},{"code":401,"indent":0,"parameters":["「はい！」"]},{"code":101,"indent":0,"parameters":["",0,0,1]},{"code":401,"indent":0,"parameters":["         Mananはいくつかの\\c[2]アイテム\\c[0]を分けてもらった！"]},{"code":126,"indent":0,"parameters":[7,0,0,5]},{"code":126,"indent":0,"parameters":[9,0,0,5]},{"code":126,"indent":0,"parameters":[11,0,0,5]},{"code":126,"indent":0,"parameters":[12,0,0,5]},{"code":126,"indent":0,"parameters":[14,0,0,5]},{"code":326,"indent":0,"parameters":[0,0,0,0,100]},{"code":224,"indent":0,"parameters":[[255,255,255,170],60,false]},{"code":241,"indent":0,"parameters":[{"name":"Battle2","volume":90,"pitch":100,"pan":0}]},{"code":314,"indent":0,"parameters":[0,0]},{"code":250,"indent":0,"parameters":[{"name":"Barrier","volume":90,"pitch":100,"pan":0}]},{"code":313,"indent":0,"parameters":[0,0,0,37]},{"code":0,"indent":0,"parameters":[]}],"span":0},{"conditions":{"actorHp":50,"actorId":1,"actorValid":false,"enemyHp":80,"enemyIndex":0,"enemyValid":true,"switchId":1,"switchValid":false,"turnA":5,"turnB":5,"turnEnding":false,"turnValid":false},"list":[{"code":337,"indent":0,"parameters":[0,37]},{"code":101,"indent":0,"parameters":["",0,1,1]},{"code":401,"indent":0,"parameters":["　　　　　　三首ケロベロスは仲間を呼んだ！"]},{"code":335,"indent":0,"parameters":[1]},{"code":335,"indent":0,"parameters":[2]},{"code":0,"indent":0,"parameters":[]}],"span":0},{"conditions":{"actorHp":50,"actorId":1,"actorValid":false,"enemyHp":60,"enemyIndex":0,"enemyValid":true,"switchId":1,"switchValid":false,"turnA":5,"turnB":5,"turnEnding":false,"turnValid":false},"list":[{"code":337,"indent":0,"parameters":[0,37]},{"code":101,"indent":0,"parameters":["",0,1,1]},{"code":401,"indent":0,"parameters":["　　　　　三首ケロベロスは再び仲間を呼んだ！"]},{"code":335,"indent":0,"parameters":[3]},{"code":335,"indent":0,"parameters":[4]},{"code":335,"indent":0,"parameters":[5]},{"code":0,"indent":0,"parameters":[]}],"span":0}]},
{"id":65,"members":[{"enemyId":72,"x":102,"y":391,"hidden":false},{"enemyId":73,"x":279,"y":394,"hidden":true}],"name":"ダークアリスベル","pages":[{"conditions":{"actorHp":50,"actorId":1,"actorValid":false,"enemyHp":50,"enemyIndex":0,"enemyValid":false,"switchId":1,"switchValid":false,"turnA":2,"turnB":2,"turnEnding":false,"turnValid":true},"list":[{"code":335,"indent":0,"parameters":[1]},{"code":337,"indent":0,"parameters":[1,57]},{"code":333,"indent":0,"parameters":[0,0,60]},{"code":0,"indent":0,"parameters":[]}],"span":0},{"conditions":{"actorHp":50,"actorId":1,"actorValid":false,"enemyHp":0,"enemyIndex":1,"enemyValid":true,"switchId":1,"switchValid":false,"turnA":0,"turnB":0,"turnEnding":false,"turnValid":false},"list":[{"code":333,"indent":0,"parameters":[0,1,60]},{"code":0,"indent":0,"parameters":[]}],"span":0}]},
{"id":66,"members":[{"enemyId":85,"x":120,"y":337,"hidden":false},{"enemyId":86,"x":90,"y":388,"hidden":true},{"enemyId":86,"x":357,"y":403,"hidden":true},{"enemyId":86,"x":204,"y":435,"hidden":true},{"enemyId":86,"x":375,"y":310,"hidden":true},{"enemyId":86,"x":285,"y":271,"hidden":true}],"name":"追憶の三首ケルベロス","pages":[{"conditions":{"actorHp":50,"actorId":1,"actorValid":false,"enemyHp":50,"enemyIndex":0,"enemyValid":false,"switchId":1,"switchValid":false,"turnA":0,"turnB":0,"turnEnding":false,"turnValid":true},"list":[{"code":326,"indent":0,"parameters":[0,0,0,0,100]},{"code":0,"indent":0,"parameters":[]}],"span":0},{"conditions":{"actorHp":50,"actorId":1,"actorValid":false,"enemyHp":80,"enemyIndex":0,"enemyValid":true,"switchId":1,"switchValid":false,"turnA":5,"turnB":5,"turnEnding":false,"turnValid":false},"list":[{"code":337,"indent":0,"parameters":[0,37]},{"code":101,"indent":0,"parameters":["",0,1,1]},{"code":401,"indent":0,"parameters":["　　　　　　三首ケロベロスは仲間を呼んだ！"]},{"code":335,"indent":0,"parameters":[1]},{"code":335,"indent":0,"parameters":[2]},{"code":0,"indent":0,"parameters":[]}],"span":0},{"conditions":{"actorHp":50,"actorId":1,"actorValid":false,"enemyHp":60,"enemyIndex":0,"enemyValid":true,"switchId":1,"switchValid":false,"turnA":5,"turnB":5,"turnEnding":false,"turnValid":false},"list":[{"code":311,"indent":0,"parameters":[0,0,0,0,50,false]},{"code":326,"indent":0,"parameters":[0,0,0,0,50]},{"code":337,"indent":0,"parameters":[0,37]},{"code":101,"indent":0,"parameters":["",0,1,1]},{"code":401,"indent":0,"parameters":["　　　　　三首ケロベロスは再び仲間を呼んだ！"]},{"code":335,"indent":0,"parameters":[3]},{"code":335,"indent":0,"parameters":[4]},{"code":335,"indent":0,"parameters":[5]},{"code":0,"indent":0,"parameters":[]}],"span":0}]},
{"id":67,"members":[],"name":"--------------","pages":[{"conditions":{"actorHp":50,"actorId":1,"actorValid":false,"enemyHp":50,"enemyIndex":0,"enemyValid":false,"switchId":1,"switchValid":false,"turnA":0,"turnB":0,"turnEnding":false,"turnValid":false},"list":[{"code":0,"indent":0,"parameters":[]}],"span":0}]},
{"id":68,"members":[{"enemyId":25,"x":267,"y":444,"hidden":false}],"name":"","pages":[{"conditions":{"actorHp":50,"actorId":1,"actorValid":false,"enemyHp":50,"enemyIndex":0,"enemyValid":false,"switchId":1,"switchValid":false,"turnA":0,"turnB":0,"turnEnding":false,"turnValid":false},"list":[{"code":0,"indent":0,"parameters":[]}],"span":0}]},
{"id":69,"members":[],"name":"","pages":[{"conditions":{"actorHp":50,"actorId":1,"actorValid":false,"enemyHp":50,"enemyIndex":0,"enemyValid":false,"switchId":1,"switchValid":false,"turnA":0,"turnB":0,"turnEnding":false,"turnValid":false},"list":[{"code":0,"indent":0,"parameters":[]}],"span":0}]},
{"id":70,"members":[{"enemyId":65,"x":225,"y":428,"hidden":false}],"name":"ヤマファンゴ","pages":[{"conditions":{"actorHp":50,"actorId":1,"actorValid":false,"enemyHp":50,"enemyIndex":0,"enemyValid":false,"switchId":1,"switchValid":false,"turnA":1,"turnB":1,"turnEnding":true,"turnValid":true},"list":[{"code":129,"indent":0,"parameters":[7,0,false]},{"code":129,"indent":0,"parameters":[8,0,false]},{"code":314,"indent":0,"parameters":[0,0]},{"code":313,"indent":0,"parameters":[0,0,0,22]},{"code":313,"indent":0,"parameters":[0,0,0,23]},{"code":313,"indent":0,"parameters":[0,0,0,54]},{"code":337,"indent":0,"parameters":[0,43]},{"code":0,"indent":0,"parameters":[]}],"span":0}]},
{"id":71,"members":[{"enemyId":74,"x":120,"y":376,"hidden":false}],"name":"yukiss","pages":[{"conditions":{"actorHp":50,"actorId":1,"actorValid":false,"enemyHp":50,"enemyIndex":0,"enemyValid":false,"switchId":1,"switchValid":false,"turnA":0,"turnB":0,"turnEnding":false,"turnValid":false},"list":[{"code":0,"indent":0,"parameters":[]}],"span":0}]},
{"id":72,"members":[{"enemyId":66,"x":153,"y":373,"hidden":false},{"enemyId":67,"x":78,"y":241,"hidden":true},{"enemyId":36,"x":360,"y":286,"hidden":true},{"enemyId":37,"x":423,"y":376,"hidden":true},{"enemyId":38,"x":333,"y":424,"hidden":true},{"enemyId":39,"x":243,"y":444,"hidden":true},{"enemyId":40,"x":69,"y":444,"hidden":true},{"enemyId":42,"x":237,"y":319,"hidden":true}],"name":"キャプテン オブ デュエリスト","pages":[{"conditions":{"actorHp":50,"actorId":1,"actorValid":false,"enemyHp":50,"enemyIndex":0,"enemyValid":false,"switchId":1,"switchValid":false,"turnA":1,"turnB":1,"turnEnding":true,"turnValid":true},"list":[{"code":129,"indent":0,"parameters":[6,0,false]},{"code":129,"indent":0,"parameters":[7,0,false]},{"code":129,"indent":0,"parameters":[12,0,false]},{"code":314,"indent":0,"parameters":[0,0]},{"code":313,"indent":0,"parameters":[0,0,0,22]},{"code":313,"indent":0,"parameters":[0,0,0,23]},{"code":313,"indent":0,"parameters":[0,0,0,54]},{"code":337,"indent":0,"parameters":[0,43]},{"code":0,"indent":0,"parameters":[]}],"span":0},{"conditions":{"actorHp":50,"actorId":1,"actorValid":false,"enemyHp":80,"enemyIndex":0,"enemyValid":true,"switchId":1,"switchValid":false,"turnA":5,"turnB":5,"turnEnding":false,"turnValid":false},"list":[{"code":337,"indent":0,"parameters":[0,37]},{"code":101,"indent":0,"parameters":["",0,1,1]},{"code":401,"indent":0,"parameters":["　　　　　　デュエリストは増援を呼んだ！"]},{"code":335,"indent":0,"parameters":[2]},{"code":0,"indent":0,"parameters":[]}],"span":0},{"conditions":{"actorHp":50,"actorId":1,"actorValid":false,"enemyHp":60,"enemyIndex":0,"enemyValid":true,"switchId":1,"switchValid":false,"turnA":5,"turnB":5,"turnEnding":false,"turnValid":false},"list":[{"code":335,"indent":0,"parameters":[3]},{"code":0,"indent":0,"parameters":[]}],"span":0},{"conditions":{"actorHp":50,"actorId":1,"actorValid":false,"enemyHp":50,"enemyIndex":0,"enemyValid":true,"switchId":1,"switchValid":false,"turnA":5,"turnB":5,"turnEnding":false,"turnValid":false},"list":[{"code":335,"indent":0,"parameters":[4]},{"code":0,"indent":0,"parameters":[]}],"span":0},{"conditions":{"actorHp":50,"actorId":1,"actorValid":false,"enemyHp":40,"enemyIndex":0,"enemyValid":true,"switchId":1,"switchValid":false,"turnA":5,"turnB":5,"turnEnding":false,"turnValid":false},"list":[{"code":335,"indent":0,"parameters":[6]},{"code":0,"indent":0,"parameters":[]}],"span":0},{"conditions":{"actorHp":50,"actorId":1,"actorValid":false,"enemyHp":35,"enemyIndex":0,"enemyValid":true,"switchId":1,"switchValid":false,"turnA":5,"turnB":5,"turnEnding":false,"turnValid":false},"list":[{"code":335,"indent":0,"parameters":[7]},{"code":0,"indent":0,"parameters":[]}],"span":0},{"conditions":{"actorHp":50,"actorId":1,"actorValid":false,"enemyHp":30,"enemyIndex":0,"enemyValid":true,"switchId":1,"switchValid":false,"turnA":5,"turnB":5,"turnEnding":false,"turnValid":false},"list":[{"code":335,"indent":0,"parameters":[1]},{"code":0,"indent":0,"parameters":[]}],"span":0}]},
{"id":73,"members":[{"enemyId":69,"x":177,"y":406,"hidden":false}],"name":"ラミア キャプテン","pages":[{"conditions":{"actorHp":50,"actorId":1,"actorValid":false,"enemyHp":50,"enemyIndex":0,"enemyValid":false,"switchId":1,"switchValid":false,"turnA":1,"turnB":1,"turnEnding":true,"turnValid":true},"list":[{"code":129,"indent":0,"parameters":[9,0,false]},{"code":129,"indent":0,"parameters":[10,0,false]},{"code":129,"indent":0,"parameters":[11,0,false]},{"code":314,"indent":0,"parameters":[0,0]},{"code":313,"indent":0,"parameters":[0,0,0,37]},{"code":0,"indent":0,"parameters":[]}],"span":0}]},
{"id":74,"members":[{"enemyId":70,"x":231,"y":427,"hidden":false}],"name":"ケルファイルギア","pages":[{"conditions":{"actorHp":50,"actorId":1,"actorValid":false,"enemyHp":50,"enemyIndex":0,"enemyValid":false,"switchId":1,"switchValid":false,"turnA":0,"turnB":0,"turnEnding":false,"turnValid":false},"list":[{"code":0,"indent":0,"parameters":[]}],"span":0}]},
{"id":75,"members":[],"name":"","pages":[{"conditions":{"actorHp":50,"actorId":1,"actorValid":false,"enemyHp":50,"enemyIndex":0,"enemyValid":false,"switchId":1,"switchValid":false,"turnA":0,"turnB":0,"turnEnding":false,"turnValid":false},"list":[{"code":0,"indent":0,"parameters":[]}],"span":0}]},
{"id":76,"members":[],"name":"","pages":[{"conditions":{"actorHp":50,"actorId":1,"actorValid":false,"enemyHp":50,"enemyIndex":0,"enemyValid":false,"switchId":1,"switchValid":false,"turnA":0,"turnB":0,"turnEnding":false,"turnValid":false},"list":[{"code":0,"indent":0,"parameters":[]}],"span":0}]},
{"id":77,"members":[],"name":"","pages":[{"conditions":{"actorHp":50,"actorId":1,"actorValid":false,"enemyHp":50,"enemyIndex":0,"enemyValid":false,"switchId":1,"switchValid":false,"turnA":0,"turnB":0,"turnEnding":false,"turnValid":false},"list":[{"code":0,"indent":0,"parameters":[]}],"span":0}]},
{"id":78,"members":[],"name":"","pages":[{"conditions":{"actorHp":50,"actorId":1,"actorValid":false,"enemyHp":50,"enemyIndex":0,"enemyValid":false,"switchId":1,"switchValid":false,"turnA":0,"turnB":0,"turnEnding":false,"turnValid":false},"list":[{"code":0,"indent":0,"parameters":[]}],"span":0}]},
{"id":79,"members":[],"name":"","pages":[{"conditions":{"actorHp":50,"actorId":1,"actorValid":false,"enemyHp":50,"enemyIndex":0,"enemyValid":false,"switchId":1,"switchValid":false,"turnA":0,"turnB":0,"turnEnding":false,"turnValid":false},"list":[{"code":0,"indent":0,"parameters":[]}],"span":0}]},
{"id":80,"members":[],"name":"","pages":[{"conditions":{"actorHp":50,"actorId":1,"actorValid":false,"enemyHp":50,"enemyIndex":0,"enemyValid":false,"switchId":1,"switchValid":false,"turnA":0,"turnB":0,"turnEnding":false,"turnValid":false},"list":[{"code":0,"indent":0,"parameters":[]}],"span":0}]}
]